xphonebr/__init__.py
xphonebr/Util/__init__.py
xphonebr/Util/norm.py
xphonebr-0.0.7.dist-info/LICENSE
xphonebr-0.0.7.dist-info/METADATA
xphonebr-0.0.7.dist-info/WHEEL
xphonebr-0.0.7.dist-info/top_level.txt
xphonebr-0.0.7.dist-info/RECORD
